Metadata-Version: 1.1
Name: peanut
Version: 1.3.7
Summary: A massively parallel GPU read mapper using OpenCL.
Home-page: http://peanut.readthedocs.org
Author: Johannes Köster
Author-email: johannes.koester@tu-dortmund.de
License: MIT
Platform: UNKNOWN
Classifier: Development Status :: 5 - Production/Stable
Classifier: Environment :: Console
Classifier: Intended Audience :: Science/Research
Classifier: License :: OSI Approved :: MIT License
Classifier: Natural Language :: English
Classifier: Programming Language :: Python :: 3
Classifier: Topic :: Scientific/Engineering :: Bio-Informatics
